HallPy_Teach/__init__.py
HallPy_Teach/constants.py
HallPy_Teach/helper.py
HallPy_Teach/experiments/__init__.py
HallPy_Teach/experiments/curieWeiss.py
HallPy_Teach/experiments/hallEffect.py
HallPy_Teach-0.1.10.dist-info/LICENSE
HallPy_Teach-0.1.10.dist-info/METADATA
HallPy_Teach-0.1.10.dist-info/WHEEL
HallPy_Teach-0.1.10.dist-info/top_level.txt
HallPy_Teach-0.1.10.dist-info/RECORD
