Metadata-Version: 2.1
Name: HallPy-Teach
Version: 0.1.10
Summary: A python library to aid physics students in performing lab activities. Developed for the School of Physics and Astronomy at the University of Glasgow.
Author-email: Shreyansh Fofandi <me@fofandi.dev>, "Dr. Ian MacLaren" <ian.maclaren@glasgow.ac.uk>
Classifier: Programming Language :: Python :: 3
Classifier: License :: Freely Distributable
Classifier: Intended Audience :: Education
Classifier: Framework :: Jupyter
Classifier: Operating System :: OS Independent
Classifier: Topic :: Education :: Computer Aided Instruction (CAI)
Requires-Python: >=3.0
License-File: LICENSE
